nanohubcitmanager/__init__.py
nanohubcitmanager/__version__.py
nanohubcitmanager/citation.py
nanohubcitmanager/client.py
nanohubcitmanager/pdf.py
nanohub_citmanager-0.1.0.dist-info/METADATA
nanohub_citmanager-0.1.0.dist-info/WHEEL
nanohub_citmanager-0.1.0.dist-info/top_level.txt
nanohub_citmanager-0.1.0.dist-info/RECORD
