Metadata-Version: 2.4
Name: nanohub-citmanager
Version: 0.1.0
Summary: A Python library for interacting with HubZero Citation Manager API
Home-page: https://github.com/denphi/nanohub-citmanager
Author: Daniel Mejia
Author-email: Daniel Mejia <denphi@denphi.com>
License: MIT
Project-URL: Homepage, https://github.com/denphi/nanohub-citmanager
Project-URL: Repository, https://github.com/denphi/nanohub-citmanager
Requires-Python: >=3.8
Requires-Dist: nanohubremote>=0.2.0
Requires-Dist: requests>=2.25.0
Provides-Extra: dev
Requires-Dist: pytest>=6.0; extra == "dev"
Requires-Dist: pytest-cov>=2.10; extra == "dev"
Requires-Dist: black>=21.0; extra == "dev"
Provides-Extra: llm
Requires-Dist: ollama>=0.1.0; extra == "llm"
Requires-Dist: openai>=1.0.0; extra == "llm"
Dynamic: author
Dynamic: home-page
Dynamic: requires-python
